relaxai/__init__.py
relaxai/_base_client.py
relaxai/_client.py
relaxai/_compat.py
relaxai/_constants.py
relaxai/_exceptions.py
relaxai/_files.py
relaxai/_models.py
relaxai/_qs.py
relaxai/_resource.py
relaxai/_response.py
relaxai/_streaming.py
relaxai/_types.py
relaxai/_version.py
relaxai/py.typed
relaxai/_utils/__init__.py
relaxai/_utils/_logs.py
relaxai/_utils/_proxy.py
relaxai/_utils/_reflection.py
relaxai/_utils/_resources_proxy.py
relaxai/_utils/_streams.py
relaxai/_utils/_sync.py
relaxai/_utils/_transform.py
relaxai/_utils/_typing.py
relaxai/_utils/_utils.py
relaxai/lib/.keep
relaxai/resources/__init__.py
relaxai/resources/chat.py
relaxai/resources/embeddings.py
relaxai/resources/models.py
relaxai/types/__init__.py
relaxai/types/chat_completion_message.py
relaxai/types/chat_completion_message_param.py
relaxai/types/chat_completion_response.py
relaxai/types/chat_create_completion_params.py
relaxai/types/content_filter_results.py
relaxai/types/embedding_create_embedding_params.py
relaxai/types/embedding_response.py
relaxai/types/function_call.py
relaxai/types/function_call_param.py
relaxai/types/function_definition_param.py
relaxai/types/health_response.py
relaxai/types/model.py
relaxai/types/model_list.py
relaxai/types/stream_options_param.py
relaxai/types/shared/__init__.py
relaxai/types/shared/openai_completion_tokens_details.py
relaxai/types/shared/openai_prompt_tokens_details.py
relaxai/types/shared/openai_usage.py
relaxai-0.18.0.dist-info/METADATA
relaxai-0.18.0.dist-info/WHEEL
relaxai-0.18.0.dist-info/licenses/LICENSE
relaxai-0.18.0.dist-info/RECORD
